rfm_market_basket_analysis/__init__.py
rfm_market_basket_analysis/association_rules.py
rfm_market_basket_analysis/main.py
rfm_market_basket_analysis/rfm_analysis.py
rfm_market_basket_analysis/visualization.py
MBA_by_RFM-0.1.0.dist-info/LICENSE
MBA_by_RFM-0.1.0.dist-info/METADATA
MBA_by_RFM-0.1.0.dist-info/WHEEL
MBA_by_RFM-0.1.0.dist-info/top_level.txt
MBA_by_RFM-0.1.0.dist-info/RECORD
