Metadata-Version: 2.1
Name: MBA_by_RFM
Version: 0.1.0
Summary: A market basket analysis for preprocessing data by RFM
Home-page: 
Author: Phalguni
Author-email: phalgunishenoy2002@gmail.com
Classifier: Programming Language :: Python :: 3
Classifier: License :: OSI Approved :: MIT License
Classifier: Operating System :: OS Independent
Requires-Python: >=3.6
License-File: LICENSE
